__init__.py
errorlib.py
kardfm.py
security.py
trun.py
pre-compile/backup.py
kardfm-0.0.1.dist-info/LICENSE
kardfm-0.0.1.dist-info/METADATA
kardfm-0.0.1.dist-info/WHEEL
kardfm-0.0.1.dist-info/top_level.txt
kardfm-0.0.1.dist-info/RECORD
